{
  "subtitle": "", 
  "uuid": "65808ce7373740118649ab53028ac2a8", 
  "language": "fre_FR", 
  "title": "histoires de fille", 
  "image": null, 
  "_version": {
    "package_version": "1.5.0", 
    "language_version": "2.7.6", 
    "language": "python", 
    "language_version_string": "2.7.6 (default, Jun 22 2015, 18:01:27) \n[GCC 4.8.2]", 
    "package": "elastic-git"
  }, 
  "slug": "girl-stories-french", 
  "source": null, 
  "position": 0, 
  "image_host": "http://thumbor.unicore.io", 
  "featured_in_navbar": false, 
  "id": null
}